lightfm_pandas/__init__.py
lightfm_pandas/evaluation.py
lightfm_pandas/data/__init__.py
lightfm_pandas/data/encoder.py
lightfm_pandas/data/features.py
lightfm_pandas/data/interactions.py
lightfm_pandas/data/datasets/__init__.py
lightfm_pandas/data/datasets/prep_movielense_data.py
lightfm_pandas/modeling/__init__.py
lightfm_pandas/modeling/base.py
lightfm_pandas/modeling/factorization_base.py
lightfm_pandas/modeling/lightfm.py
lightfm_pandas/utils/__init__.py
lightfm_pandas/utils/array_math.py
lightfm_pandas/utils/config.py
lightfm_pandas/utils/instrumentation.py
lightfm_pandas/utils/logging_config.py
lightfm_pandas/utils/testing.py
lightfm_pandas-0.2.1.dist-info/LICENSE
lightfm_pandas-0.2.1.dist-info/METADATA
lightfm_pandas-0.2.1.dist-info/WHEEL
lightfm_pandas-0.2.1.dist-info/top_level.txt
lightfm_pandas-0.2.1.dist-info/RECORD
